nextc/__init__.py
nextc/__main__.py
nextc/ast/__init__.py
nextc/compile/__init__.py
nextc/compile/core.py
nextc/compile/declarations.py
nextc/lexing/__init__.py
nextc/lexing/errors.py
nextc/lexing/token.py
nextc/lexing/tokenizer.py
nextc/parse/__init__.py
nextc/runtime/.gitkeep
nextc-0.2.dist-info/WHEEL
nextc-0.2.dist-info/METADATA
nextc-0.2.dist-info/RECORD
